simple_gcp_connector/__init__.py
simple_gcp_connector/cloud_sql.py
simple_gcp_connector/psycopg.py
simple_gcp_connector/py.typed
simple_gcp_connector/sqlalchemy.py
simple_gcp_connector/token_provider.py
simple_gcp_connector-0.1.4.dist-info/WHEEL
simple_gcp_connector-0.1.4.dist-info/METADATA
simple_gcp_connector-0.1.4.dist-info/RECORD
