Metadata-Version: 2.4
Name: simple-gcp-connector
Version: 0.1.4
Summary: A simple connector for GCP databases
Author: Rob Clevenger
Author-email: Rob Clevenger <rob@robsite.org>
License-Expression: Apache-2.0
Requires-Dist: google-auth>=2.43.0
Requires-Dist: requests>=2.32.5
Requires-Dist: psycopg>=3.1.0 ; extra == 'psycopg-pool'
Requires-Dist: psycopg-pool>=3.1.0 ; extra == 'psycopg-pool'
Requires-Dist: sqlalchemy>=2.0.0 ; extra == 'sqlalchemy'
Requires-Python: >=3.13
Project-URL: Homepage, https://github.com/rcleveng/simple_gcp_connector
Project-URL: Issues, https://github.com/rcleveng/simple_gcp_connector/issues
Provides-Extra: psycopg-pool
Provides-Extra: sqlalchemy
